dm_job_utilities/__init__.py
dm_job_utilities/dm_log.py
dm_job_utilities/utils.py
im_data_manager_job_utilities-1.2.1.dist-info/licenses/LICENSE
im_data_manager_job_utilities-1.2.1.dist-info/METADATA
im_data_manager_job_utilities-1.2.1.dist-info/WHEEL
im_data_manager_job_utilities-1.2.1.dist-info/top_level.txt
im_data_manager_job_utilities-1.2.1.dist-info/RECORD
