Metadata-Version: 2.4
Name: im-data-manager-job-utilities
Version: 1.2.1
Summary: Job execution utilities
Home-page: https://github.com/informaticsmatters/squonk2-data-manager-job-utilities
Author: Alan Christie
Author-email: achristie@informaticsmatters.com
License: MIT
Keywords: logging
Platform: any
Classifier: Development Status :: 5 - Production/Stable
Classifier: Environment :: Other Environment
Classifier: Intended Audience :: Developers
Classifier: License :: OSI Approved :: MIT License
Classifier: Programming Language :: Python :: 3.10
Classifier: Programming Language :: Python :: 3.11
Classifier: Topic :: Software Development :: Libraries :: Python Modules
Classifier: Operating System :: POSIX :: Linux
License-File: LICENSE
Requires-Dist: pytz==2025.2
Requires-Dist: six==1.17.0
Requires-Dist: wrapt==1.17.3
Dynamic: author
Dynamic: author-email
Dynamic: classifier
Dynamic: description
Dynamic: home-page
Dynamic: keywords
Dynamic: license
Dynamic: license-file
Dynamic: platform
Dynamic: requires-dist
Dynamic: summary
